tau_trait/__init__.py
tau_trait/run.py
tau_trait/types.py
tau_trait/agents/__init__.py
tau_trait/agents/base.py
tau_trait/agents/chat_react_agent.py
tau_trait/agents/few_shot_agent.py
tau_trait/agents/tool_calling_agent.py
tau_trait/assets/collinear.png
tau_trait/assets/release-batch.svg
tau_trait/envs/__init__.py
tau_trait/envs/base.py
tau_trait/envs/tool.py
tau_trait/envs/user.py
tau_trait/envs/user_assistants.py
tau_trait/envs/airline/__init__.py
tau_trait/envs/airline/env.py
tau_trait/envs/airline/rules.py
tau_trait/envs/airline/tasks.py
tau_trait/envs/airline/tasks_test.py
tau_trait/envs/airline/wiki.md
tau_trait/envs/airline/wiki.py
tau_trait/envs/airline/data/__init__.py
tau_trait/envs/airline/data/flights.json
tau_trait/envs/airline/data/reservations.json
tau_trait/envs/airline/data/users.json
tau_trait/envs/airline/tools/__init__.py
tau_trait/envs/airline/tools/book_reservation.py
tau_trait/envs/airline/tools/calculate.py
tau_trait/envs/airline/tools/cancel_reservation.py
tau_trait/envs/airline/tools/get_reservation_details.py
tau_trait/envs/airline/tools/get_user_details.py
tau_trait/envs/airline/tools/list_all_airports.py
tau_trait/envs/airline/tools/search_direct_flight.py
tau_trait/envs/airline/tools/search_onestop_flight.py
tau_trait/envs/airline/tools/send_certificate.py
tau_trait/envs/airline/tools/think.py
tau_trait/envs/airline/tools/transfer_to_human_agents.py
tau_trait/envs/airline/tools/update_reservation_baggages.py
tau_trait/envs/airline/tools/update_reservation_flights.py
tau_trait/envs/airline/tools/update_reservation_passengers.py
tau_trait/envs/retail/__init__.py
tau_trait/envs/retail/env.py
tau_trait/envs/retail/rules.py
tau_trait/envs/retail/tasks.py
tau_trait/envs/retail/tasks_dev.py
tau_trait/envs/retail/tasks_test.py
tau_trait/envs/retail/tasks_train.py
tau_trait/envs/retail/wiki.md
tau_trait/envs/retail/wiki.py
tau_trait/envs/retail/data/__init__.py
tau_trait/envs/retail/data/orders.json
tau_trait/envs/retail/data/products.json
tau_trait-0.1.1.dist-info/licenses/LICENSE
tau_trait-0.1.1.dist-info/METADATA
tau_trait-0.1.1.dist-info/WHEEL
tau_trait-0.1.1.dist-info/top_level.txt
tau_trait-0.1.1.dist-info/RECORD
