Metadata-Version: 2.4
Name: tau_trait
Version: 0.1.1
Summary: The Tau-Trait package
License-File: LICENSE
Requires-Dist: openai>=1.13.3
Requires-Dist: mistralai>=0.4.0
Requires-Dist: anthropic>=0.26.1
Requires-Dist: google-generativeai>=0.5.4
Requires-Dist: tenacity>=8.3.0
Requires-Dist: termcolor>=2.4.0
Requires-Dist: numpy>=1.26.4
Requires-Dist: litellm>=1.41.0
Dynamic: description
Dynamic: description-content-type
Dynamic: license-file
Dynamic: requires-dist
Dynamic: summary
